{
  "$schema": "http://json-schema.org/draft-07/schema",
  "type": "object",
  "required": ["format_version", "minecraft:fossil_feature"],
  "properties": {
    "format_version": { "type": "string" },
    "minecraft:fossil_feature": {
      "type": "object",
      "required": ["description"],
      "properties": {
        "description": {
          "type": "object",
          "required": ["identifier"],
          "properties": {
            "identifier": {
              "type": "string"
            }
          },
          "additionalProperties": false
        },
        "ore_block": { "type": "string" },
        "max_empty_corners": { "type": "integer" }
      },
      "additionalProperties": false
    }
  },
  "additionalProperties": false
}
